CertCenter.py
CertCenter-1.13.3.dist-info/DESCRIPTION.rst
CertCenter-1.13.3.dist-info/METADATA
CertCenter-1.13.3.dist-info/RECORD
CertCenter-1.13.3.dist-info/WHEEL
CertCenter-1.13.3.dist-info/metadata.json
CertCenter-1.13.3.dist-info/top_level.txt
