Metadata-Version: 2.0
Name: CertCenter
Version: 1.13.3
Summary: The official CertCenter API library
Home-page: https://github.com/CertCenter/pyCertCenter
Author: CertCenter Development Team
Author-email: pyCertCenter-dev@certcenter.com
License: MIT
Keywords: SSL TLS Encryption Certificates CertCenter Sockets
Platform: UNKNOWN
Classifier: Development Status :: 4 - Beta
Classifier: Environment :: Plugins
Classifier: Intended Audience :: Developers
Classifier: Topic :: Security :: Cryptography
Classifier: License :: OSI Approved :: MIT License
Classifier: Operating System :: OS Independent
Classifier: Programming Language :: Python
Classifier: Topic :: Software Development :: Libraries
